[
    {
        "chapterId":1,
        "chapterNumber":1,
        "title":"The End and a Beginning",
        "contentwarnings":[
            "Fallen Universe"
        ],
        "genre":[
            "Example",
            "Fantasy"
        ],
        "author":"Spencer Zaugg",
        "previous":null,
        "branches": [2,3],
        "path":"stories/the_moonlit_alchemist_spencer_zaugg/1_the_end_and_a_beginning_spencer_zaugg"
    },
    {
        "chapterId":2,
        "chapterNumber":2,
        "title":"Seeking a New Home",
        "contentwarnings":[
            "Fallen Universe"
        ],
        "genre":[
            "Example",
            "Fantasy"
        ],
        "author":"Spencer Zaugg",
        "previous":1,
        "branches": [],
        "path":"stories/the_moonlit_alchemist_spencer_zaugg/2_seeking_a_new_home"
    },
    {
        "chapterId":3,
        "chapterNumber":2,
        "title":"A new Friend",
        "contentwarnings":[
            "Fallen Universe"
        ],
        "genre":[
            "Example",
            "Fantasy"
        ],
        "author":"Spencer Zaugg",
        "previous":1,
        "branches": [],
        "path":"stories/the_moonlit_alchemist_spencer_zaugg/3_a_new_friend"
    }
]